setup.cfg
setup.py
tobd/__init__.py
tobd/tobd.py
tobd.egg-info/PKG-INFO
tobd.egg-info/SOURCES.txt
tobd.egg-info/dependency_links.txt
tobd.egg-info/top_level.txt