Metadata-Version: 2.1
Name: tobd
Version: 1.0.0
Summary: dangerous
Author: NuatStanskiy
Author-email: smiril13@mail.ru
License: Apache License, Version 2.0, see LICENSE file
